{"rabbit_version":"3.13.0","rabbitmq_version":"3.13.0","product_name":"RabbitMQ","product_version":"3.13.0","users":[{"name":"guest","password_hash":"1+Edzj9cGlsJKUUmfdEmihZSnEldvDfEuQ139kNF7uz43+4Q","hashing_algorithm":"rabbit_password_hashing_sha256","tags":["administrator"],"limits":{}}],"vhosts":[{"name":"/"}],"permissions":[{"user":"guest","vhost":"/","configure":".*","write":".*","read":".*"}],"topic_permissions":[],"parameters":[],"global_parameters":[{"name":"internal_cluster_id","value":"rabbitmq-cluster-id-HBFGAiXmtdySGgRvd8JLlA"}],"policies":[],"queues":[{"name":"Events.Nashville","vhost":"/","durable":true,"auto_delete":false,"arguments":{}},{"name":"Events.Franklin","vhost":"/","durable":true,"auto_delete":false,"arguments":{}}],"exchanges":[{"name":"DIRECT","vhost":"/","type":"direct","durable":true,"auto_delete":false,"internal":false,"arguments":{}}],"bindings":[{"source":"DIRECT","vhost":"/","destination":"Events.Franklin","destination_type":"queue","routing_key":"Events.Franklin","arguments":{}},{"source":"DIRECT","vhost":"/","destination":"Events.Nashville","destination_type":"queue","routing_key":"Events.Nashville","arguments":{}}]}